LICENSE
README.md
__init__.py
sdk_utils.py
setup.cfg
setup.py
vl_device_http.py
vl_device_mqtt.py
vl_gateway_mqtt.py
vl_mqtt_client.egg-info/PKG-INFO
vl_mqtt_client.egg-info/SOURCES.txt
vl_mqtt_client.egg-info/dependency_links.txt
vl_mqtt_client.egg-info/requires.txt
vl_mqtt_client.egg-info/top_level.txt