Metadata-Version: 2.1
Name: vl-mqtt-client
Version: 1.3
Summary: ViraLink python client SDK
Home-page: https://github.com/viralinkio/viralink-python-client-sdk
Author: Viralink
Author-email: info@viralink.io
License: Apache Software License (Apache Software License 2.0)
Download-URL: https://github.com/viralinkio/viralink-python-client-sdk/archive/1.3.tar.gz
Platform: UNKNOWN
Requires-Python: >=3.6
License-File: LICENSE
